linlinegg_mcp_calculator/__init__.py
linlinegg_mcp_calculator/server.py
linlinegg_mcp_calculator_server-0.1.0.dist-info/METADATA
linlinegg_mcp_calculator_server-0.1.0.dist-info/WHEEL
linlinegg_mcp_calculator_server-0.1.0.dist-info/entry_points.txt
linlinegg_mcp_calculator_server-0.1.0.dist-info/licenses/LICENSE
linlinegg_mcp_calculator_server-0.1.0.dist-info/RECORD
