Metadata-Version: 2.4
Name: linlinegg-mcp-calculator-server
Version: 0.1.0
Summary: 一个简单的 MCP 服务器，提供计算器、时间和天气查询功能
Project-URL: Homepage, https://github.com/linlinegg/mcp-calculator-server
Project-URL: Documentation, https://github.com/linlinegg/mcp-calculator-server#readme
Project-URL: Repository, https://github.com/linlinegg/mcp-calculator-server
Project-URL: Issues, https://github.com/linlinegg/mcp-calculator-server/issues
Author-email: Linlinegg <your.email@example.com>
License: MIT License
License-File: LICENSE
Keywords: calculator,claude,cursor,mcp,model-context-protocol
Classifier: Development Status :: 3 - Alpha
Classifier: Intended Audience :: Developers
Classifier: License :: OSI Approved :: MIT License
Classifier: Programming Language :: Python :: 3
Classifier: Programming Language :: Python :: 3.8
Classifier: Programming Language :: Python :: 3.9
Classifier: Programming Language :: Python :: 3.10
Classifier: Programming Language :: Python :: 3.11
Classifier: Programming Language :: Python :: 3.12
Classifier: Topic :: Software Development :: Libraries :: Python Modules
Requires-Python: >=3.8
Requires-Dist: mcp>=1.0.0
Provides-Extra: dev
Requires-Dist: black>=23.0.0; extra == 'dev'
Requires-Dist: mypy>=1.0.0; extra == 'dev'
Requires-Dist: pytest>=7.0.0; extra == 'dev'
Requires-Dist: ruff>=0.1.0; extra == 'dev'
